badpy
