Metadata-Version: 2.1
Name: badpy
Version: 1.4
Summary: Python package for hacking. (This package including hacking modules.)
Home-page: UNKNOWN
Author: TheSadError
Author-email: syntaxerrorses@gmail.com
License: MIT
Keywords: hack,package,python package for hacking,pythonda hack paketleri,pentest library,pentesting,TheSadError
Platform: UNKNOWN
